ibge/__init__.py
ibge/brasil/__init__.py
ibge/data/ibge.duckdb
ibge/sql/__init__.py
ibge/tests/__init__.py
ibge/tests/test_duckdb.py
ibge/tests/test_ibge_brasil.py
ibge_utils-1.0.1.dist-info/LICENSE
ibge_utils-1.0.1.dist-info/METADATA
ibge_utils-1.0.1.dist-info/WHEEL
ibge_utils-1.0.1.dist-info/RECORD
