Metadata-Version: 2.1
Name: ibge-utils
Version: 1.0.1
Summary: Utility Python package for IBGE information
License: GNU General Public License v3.0
Author: Luã Bida Vacaro
Author-email: luabidaa@gmail.com
Requires-Python: >=3.9,<4
Classifier: Development Status :: 3 - Alpha
Classifier: Intended Audience :: Developers
Classifier: License :: OSI Approved :: GNU General Public License v3 or later (GPLv3+)
Classifier: License :: Other/Proprietary License
Classifier: Operating System :: OS Independent
Classifier: Programming Language :: Python :: 3
Classifier: Programming Language :: Python :: 3.9
Classifier: Programming Language :: Python :: 3.10
Classifier: Programming Language :: Python :: 3.11
Classifier: Programming Language :: Python :: 3.12
Classifier: Topic :: Software Development :: Libraries :: Python Modules
Requires-Dist: duckdb (>=0.9.2,<0.10.0)
Requires-Dist: pandas (>=2.1.4,<3.0.0)
